<annotation>
	<folder />
	<filename>IMG_20230708_185220_jpg.rf.9472dd3b56abe7fa81bbd8a56e9efc9b.jpg</filename>
	<path>IMG_20230708_185220_jpg.rf.9472dd3b56abe7fa81bbd8a56e9efc9b.jpg</path>
	<source>
		<database>roboflow.com</database>
	</source>
	<size>
		<width>4640</width>
		<height>3472</height>
		<depth>3</depth>
	</size>
	<segmented>0</segmented>
	<object>
		<name>plastic bottle</name>
		<pose>Unspecified</pose>
		<truncated>0</truncated>
		<difficult>0</difficult>
		<occluded>0</occluded>
		<bndbox>
			<xmin>531</xmin>
			<xmax>2158</xmax>
			<ymin>624</ymin>
			<ymax>1606</ymax>
		</bndbox>
	</object>
	<object>
		<name>plastic bottle</name>
		<pose>Unspecified</pose>
		<truncated>0</truncated>
		<difficult>0</difficult>
		<occluded>0</occluded>
		<bndbox>
			<xmin>1914</xmin>
			<xmax>2414</xmax>
			<ymin>1328</ymin>
			<ymax>2294</ymax>
		</bndbox>
	</object>
	<object>
		<name>plastic bottle</name>
		<pose>Unspecified</pose>
		<truncated>0</truncated>
		<difficult>0</difficult>
		<occluded>0</occluded>
		<bndbox>
			<xmin>2554</xmin>
			<xmax>3094</xmax>
			<ymin>1555</ymin>
			<ymax>2061</ymax>
		</bndbox>
	</object>
	<object>
		<name>plastic bottle</name>
		<pose>Unspecified</pose>
		<truncated>0</truncated>
		<difficult>0</difficult>
		<occluded>0</occluded>
		<bndbox>
			<xmin>1736</xmin>
			<xmax>3625</xmax>
			<ymin>1882</ymin>
			<ymax>2594</ymax>
		</bndbox>
	</object>
	</annotation>